.flake8
.gitignore
.travis.yml
CHANGELOG.rst
LICENSE
README.rst
pyproject.toml
setup.cfg
setup.py
tox.ini
elastic2_doc_manager_transaction.egg-info/PKG-INFO
elastic2_doc_manager_transaction.egg-info/SOURCES.txt
elastic2_doc_manager_transaction.egg-info/dependency_links.txt
elastic2_doc_manager_transaction.egg-info/requires.txt
elastic2_doc_manager_transaction.egg-info/top_level.txt
mongo_connector/__init__.py
mongo_connector/doc_managers/__init__.py
mongo_connector/doc_managers/elastic2_doc_manager.py
tests/__init__.py
tests/test_elastic2.py
tests/test_elastic2_doc_manager.py