Metadata-Version: 2.1
Name: elastic2-doc-manager-transaction
Version: 1.2.0
Summary: es2 for mongo-connector
Home-page: https://github.com/AmrAdelKhalil/elastic2-doc-manager
Author: Amr Adel
Author-email: amradelkhalil@gmail.com
Maintainer: mongodb
License: UNKNOWN
Keywords: mongo-connector-transaction,mongodb,elastic,elasticsearch,transaction
Platform: any
Classifier: Development Status :: 4 - Beta
Classifier: Intended Audience :: Developers
Classifier: License :: OSI Approved :: Apache Software License
Classifier: Programming Language :: Python :: 3
Classifier: Topic :: Database
Classifier: Topic :: Software Development :: Libraries :: Python Modules
Classifier: Operating System :: Unix
Classifier: Operating System :: MacOS :: MacOS X
Classifier: Operating System :: Microsoft :: Windows
Classifier: Operating System :: POSIX
Requires-Python: >=3.4
Provides-Extra: aws
Provides-Extra: elastic2
Provides-Extra: elastic5
License-File: LICENSE
